[
  {
    "chunk_id": "1705.03122v3.tei.tei_chunk-1",
    "paper_id": "1705.03122v3.tei.tei",
    "section": null,
    "paragraph_index": 0,
    "text": "**Published:** 25 Jul 2017\n\nThe prevalent approach to sequence to sequence learning maps an input sequence to a variable length\noutput sequence via recurrent neural networks. We introduce an architecture based entirely on\nconvolutional neural networks. 1 Compared to recurrent models, computations over all elements can be\nfully parallelized during training to better exploit the GPU hardware and optimization is easier\nsince the number of non-linearities is fixed and independent of the input length. Our use of gated\nlinear units eases gradient propagation and we equip each decoder layer with a separate attention\nmodule. We outperform the accuracy of the deep LSTM setup of Wu et al. (2016) on both WMT'14\nEnglish-German and WMT'14 English-French translation at an order of magnitude faster speed, both on\nGPU and CPU.\n\nSequence to sequence learning has been successful in many tasks such as machine translation, speech\nrecognition (Sutskever et al., 2014;Chorowski et al., 2015) and text summarization (Rush et al.,\n2015;Nallapati et al., 2016;Shen et al., 2016) amongst others. The dominant approach to date encodes\nthe input sequence with a series of bi-directional recurrent neural networks (RNN) and generates a\nvariable length output with another set of decoder RNNs, both of which interface via a soft-\nattention mechanism (Bahdanau et al., 2014;Luong et al., 2015). In machine translation, this\narchitecture has been demonstrated to outperform traditional phrase-based models by large margins\n(Sennrich et al., 2016b;Zhou et al., 2016;Wu et al., 2016;§2).\n\nConvolutional neural networks are less common for sequence modeling, despite several advantages\n(Waibel et al., 1989;LeCun & Bengio, 1995). Compared to recurrent layers, convolutions create\nrepresentations for fixed size contexts, however, the effective context size of the network can\neasily be made larger by stacking several layers on top of each other. This allows to precisely\ncontrol the maximum length of dependencies to be modeled. Convolutional networks do not depend on\nthe computations of the previous time step and therefore allow parallelization over every element in\na sequence. This contrasts with RNNs which maintain a hidden state of the entire past that prevents\nparallel computation within a sequence.",
    "year": 2017
  },
  {
    "chunk_id": "1705.03122v3.tei.tei_chunk-2",
    "paper_id": "1705.03122v3.tei.tei",
    "section": "1. Introduction",
    "paragraph_index": 4,
    "text": "Multi-layer convolutional neural networks create hierarchical representations over the input\nsequence in which nearby input elements interact at lower layers while distant elements interact at\nhigher layers. Hierarchical structure provides a shorter path to capture long-range dependencies\ncompared to the chain structure modeled by recurrent networks, e.g. we can obtain a feature\nrepresentation capturing relationships within a window of n words by applying only O( n k )\nconvolutional operations for kernels of width k, compared to a linear number O(n) for recurrent\nneural networks. Inputs to a convolutional network are fed through a constant number of kernels and\nnon-linearities, whereas recurrent networks apply up to n operations and non-linearities to the\nfirst word and only a single set of operations to the last word. Fixing the number of nonlinearities\napplied to the inputs also eases learning.\n\nRecent work has applied convolutional neural networks to sequence modeling such as Bradbury et al.\n(2016) who introduce recurrent pooling between a succession of convolutional layers or Kalchbrenner\net al. (2016) who tackle neural translation without attention. However, none of these approaches has\nbeen demonstrated improvements over state of the art results on large benchmark datasets. Gated\nconvolutions have been previously explored for machine translation by Meng et al. (2015) but their\nevaluation was restricted to a small dataset and the model was used in tandem with a traditional\ncount-based model. Architec-tures which are partially convolutional have shown strong performance on\nlarger tasks but their decoder is still recurrent (Gehring et al., 2016).\n\nIn this paper we propose an architecture for sequence to sequence modeling that is entirely\nconvolutional. Our model is equipped with gated linear units (Dauphin et al., 2016) and residual\nconnections (He et al., 2015a). We also use attention in every decoder layer and demonstrate that\neach attention layer only adds a negligible amount of overhead. The combination of these choices\nenables us to tackle large scale problems ( §3).",
    "year": 2017
  },
  {
    "chunk_id": "1705.03122v3.tei.tei_chunk-3",
    "paper_id": "1705.03122v3.tei.tei",
    "section": "1. Introduction",
    "paragraph_index": 7,
    "text": "We evaluate our approach on several large datasets for machine translation as well as summarization\nand compare to the current best architectures reported in the literature. On WMT'16 English-Romanian\ntranslation we achieve a new state of the art, outperforming the previous best result by 1.9 BLEU.\nOn WMT'14 English-German we outperform the strong LSTM setup of Wu et al. (2016) by 0.5 BLEU and on\nWMT'14 English-French we outperform the likelihood trained system of Wu et al. (2016) by 1.6 BLEU.\nFurthermore, our model can translate unseen sentences at an order of magnitude faster speed than Wu\net al. (2016) on GPU and CPU hardware ( §4, §5).\n\nSequence to sequence modeling has been synonymous with recurrent neural network based encoder-\ndecoder architectures (Sutskever et al., 2014;Bahdanau et al., 2014). The encoder RNN processes an\ninput sequence x = (x 1 , . . . , x m ) of m elements and returns state representations z = (z 1 . .\n. . , z m ). The decoder RNN takes z and generates the output sequence y = (y 1 , . . . , y n ) left\nto right, one element at a time. To generate output y i+1 , the decoder computes a new hidden state\nh i+1 based on the previous state h i , an embedding g i of the previous target language word y i ,\nas well as a conditional input c i derived from the encoder output z. Based on this generic\nformulation, various encoder-decoder architectures have been proposed, which differ mainly in the\nconditional input and the type of RNN.\n\nModels without attention consider only the final encoder state z m by setting c i = z m for all i\n(Cho et al., 2014), or simply initialize the first decoder state with z m (Sutskever et al., 2014),\nin which case c i is not used. Architectures with attention (Bahdanau et al., 2014;Luong et al.,\n2015) compute c i as a weighted sum of (z 1 . . . . , z m ) at each time step. The weights of the\nsum are referred to as attention scores and allow the network to focus on different parts of the\ninput sequence as it generates the output sequences. Attention scores are computed by essentially\ncomparing each encoder state z j to a combination of the previous decoder state h i and the last\nprediction y i ; the result is normalized to be a distribution over input elements.",
    "year": 2017
  },
  {
    "chunk_id": "1705.03122v3.tei.tei_chunk-4",
    "paper_id": "1705.03122v3.tei.tei",
    "section": "2. Recurrent Sequence to Sequence Learning",
    "paragraph_index": 10,
    "text": "Popular choices for recurrent networks in encoder-decoder models are long short term memory networks\n(LSTM; Hochreiter & Schmidhuber, 1997) and gated recurrent units (GRU; Cho et al., 2014). Both\nextend Elman RNNs (Elman, 1990) with a gating mechanism that allows the memorization of information\nfrom previous time steps in order to model long-term dependencies. Most recent approaches also rely\non bi-directional encoders to build representations of both past and future contexts (Bahdanau et\nal., 2014;Zhou et al., 2016;Wu et al., 2016). Models with many layers often rely on shortcut or\nresidual connections (He et al., 2015a;Zhou et al., 2016;Wu et al., 2016).\n\nNext we introduce a fully convolutional architecture for sequence to sequence modeling. Instead of\nrelying on RNNs to compute intermediate encoder states z and decoder states h we use convolutional\nneural networks (CNN).\n\nFirst, we embed input elements x = (x 1 , . . . , x m ) in distributional space as w = (w 1 , . . .\n, w m ), where w j ∈ R f is a column in an embedding matrix D ∈ R V ×f . We also equip our model\nwith a sense of order by embedding the absolute position of input elements p = (p 1 , . . . , p m )\nwhere p j ∈ R f . Both are combined to obtain input element representations e = (w 1 + p 1 , . . . ,\nw m + p m ). We proceed similarly for output elements that were already generated by the decoder\nnetwork to yield output element representations that are being fed back into the decoder network g =\n(g 1 , . . . , g n ). Position embeddings are useful in our architecture since they give our model a\nsense of which portion of the sequence in the input or output it is currently dealing with ( §5.4).",
    "year": 2017
  },
  {
    "chunk_id": "1705.03122v3.tei.tei_chunk-5",
    "paper_id": "1705.03122v3.tei.tei",
    "section": "3.2. Convolutional Block Structure",
    "paragraph_index": 13,
    "text": "Both encoder and decoder networks share a simple block structure that computes intermediate states\nbased on a fixed number of input elements. We denote the output of the lth block as h l = (h l 1 , .\n. . , h l n ) for the decoder network, and z l = (z l 1 , . . . , z l m ) for the encoder network;\nwe refer to blocks and layers interchangeably. Each block contains a one dimensional convolution\nfollowed by a non-linearity. For a decoder network with a single block and kernel width k, each\nresulting state h 1 i contains information over k input elements. Stacking several blocks on top of\neach other increases the number of input elements represented in a state. For instance, stacking 6\nblocks with k = 5 results in an input field of 25 elements, i.e. each output depends on 25 inputs.\nNon-linearities allow the networks to exploit the full input field, or to focus on fewer elements if\nneeded.\n\nEach convolution kernel is parameterized as W ∈ R 2d×kd , b w ∈ R 2d and takes as input X ∈ R k×d\nwhich is a concatenation of k input elements embedded in d dimensions and maps them to a single\noutput element Y ∈ R 2d that has twice the dimensionality of the input elements; subsequent layers\noperate over the k output elements of the previous layer. We choose gated linear units (GLU; Dauphin\net al., 2016) as non-linearity which implement a simple gating mechanism over the output of the\nconvolution\n\nwhere A, B ∈ R d are the inputs to the non-linearity, ⊗ is the point-wise multiplication and the\noutput v([A B]) ∈ R d is half the size of Y . The gates σ(B) control which inputs A of the current\ncontext are relevant. A similar nonlinearity has been introduced in Oord et al. (2016b) who apply\ntanh to A but Dauphin et al. (2016) shows that GLUs perform better in the context of language\nmodelling.",
    "year": 2017
  },
  {
    "chunk_id": "1705.03122v3.tei.tei_chunk-6",
    "paper_id": "1705.03122v3.tei.tei",
    "section": "3.2. Convolutional Block Structure",
    "paragraph_index": 16,
    "text": "To enable deep convolutional networks, we add residual connections from the input of each\nconvolution to the output of the block (He et al., 2015a).\n\nFor encoder networks we ensure that the output of the convolutional layers matches the input length\nby padding the input at each layer. However, for decoder networks we have to take care that no\nfuture information is available to the decoder (Oord et al., 2016a). Specifically, we pad the input\nby k -1 elements on both the left and right side by zero vectors, and then remove k elements from\nthe end of the convolution output.\n\nWe also add linear mappings to project between the embedding size f and the convolution outputs that\nare of size 2d.\n\nWe apply such a transform to w when feeding embeddings to the encoder network, to the encoder output\nz u j , to the final layer of the decoder just before the softmax h L , and to all decoder layers h\nl before computing attention scores (1).\n\nFinally, we compute a distribution over the T possible next target elements y i+1 by transforming\nthe top decoder output h L i via a linear layer with weights W o and bias b o :\n\nWe introduce a separate attention mechanism for each decoder layer. To compute the attention, we\ncombine the current decoder state h l i with an embedding of the previous target element g i :\n\nFor decoder layer l the attention a l ij of state i and source element j is computed as a dot-\nproduct between the decoder state summary d l i and each output z u j of the last encoder block u:\n\nThe conditional input c l i to the current decoder layer is a weighted sum of the encoder outputs as\nwell as the input element embeddings e j (Figure 1, center right):\n\nThis is slightly different to recurrent approaches which compute both the attention and the weighted\nsum over z u j only. We found adding e j to be beneficial and it resembles key-value memory networks\nwhere the keys are the z u j and the values are the z u j + e j (Miller et al., 2016). Encoder\noutputs z u j represent potentially large input contexts and e j provides point information about a\nspecific input element that is useful when making a prediction. Once c l i has been computed, it is\nsimply added to the output of the corresponding decoder layer h l i . This can be seen as attention\nwith multiple 'hops' (Sukhbaatar et al., 2015) compared to single step attention (Bahdanau et al.,\n2014;Luong et al., 2015;Zhou et al., 2016;Wu et al., 2016). In particular, the attention of the\nfirst layer determines a useful source context which is then fed to the second layer that takes this\ninformation into account when computing attention etc. The decoder also has immediate access to the\nattention history of the k -1 previous time steps because the conditional inputs",
    "year": 2017
  },
  {
    "chunk_id": "1705.03122v3.tei.tei_chunk-7",
    "paper_id": "1705.03122v3.tei.tei",
    "section": "3.3. Multi-step Attention",
    "paragraph_index": 25,
    "text": "This makes it easier for the model to take into account which previous inputs have been attended to\nalready compared to recurrent nets where this information is in the recurrent state and needs to\nsurvive several non-linearities. Overall, our attention mechanism considers which words we\npreviously attended to (Yang et al., 2016) and performs multiple attention 'hops' per time step. In\nAppendix §C, we plot attention scores for a deep decoder and show that at different layers,\ndifferent portions of the source are attended to.\n\nOur convolutional architecture also allows to batch the attention computation across all elements of\na sequence compared to RNNs (Figure 1, middle). We batch the computations of each decoder layer\nindividually.\n\nWe stabilize learning through careful weight initialization ( §3.5) and by scaling parts of the\nnetwork to ensure that the variance throughout the network does not change dramatically. In\nparticular, we scale the output of residual blocks as well as the attention to preserve the variance\nof activations. We multiply the sum of the input and output of a residual block by √ 0.5 to halve\nthe variance of the sum. This assumes that both summands have the same variance which is not always\ntrue but effective in practice.\n\nThe conditional input c l i generated by the attention is a weighted sum of m vectors (2) and we\ncounteract a change in variance through scaling by m 1/m; we multiply by m to scale up the inputs to\ntheir original size, assuming the attention scores are uniformly distributed. This is generally not\nthe case but we found it to work well in practice.\n\nFor convolutional decoders with multiple attention, we scale the gradients for the encoder layers by\nthe number of attention mechanisms we use; we exclude source word embeddings. We found this to\nstabilize learning since the encoder received too much gradient otherwise.\n\nNormalizing activations when adding the output of different layers, e.g. residual connections,\nrequires careful weight initialization. The motivation for our initialization is the same as for the\nnormalization: maintain the variance of activations throughout the forward and backward passes. All\nembeddings are initialized from a normal distribution with mean 0 and standard deviation 0.1. For\nlayers whose output is not directly fed to a gated linear unit, we initialize weights from N (0, 1/n\nl ) where n l is the number of input connections to each neuron. This ensures that the variance of a\nnormally distributed input is retained.",
    "year": 2017
  },
  {
    "chunk_id": "1705.03122v3.tei.tei_chunk-8",
    "paper_id": "1705.03122v3.tei.tei",
    "section": "3.5. Initialization",
    "paragraph_index": 31,
    "text": "For layers which are followed by a GLU activation, we propose a weight initialization scheme by\nadapting the derivations in (He et al., 2015b;Glorot & Bengio, 2010; Appendix A). If the GLU inputs\nare distributed with mean 0 and have sufficiently small variance, then we can approximate the output\nvariance with 1/4 of the input variance (Appendix A.1). Hence, we initialize the weights so that the\ninput to the GLU activations have 4 times the variance of the layer input. This is achieved by\ndrawing their initial values from N (0, 4/n l ). Biases are uniformly set to zero when the network\nis constructed.\n\nWe apply dropout to the input of some layers so that inputs are retained with a probability of p.\nThis can be seen as multiplication with a Bernoulli random variable taking value 1/p with\nprobability p and 0 otherwise (Srivastava et al., 2014). The application of dropout will then cause\nthe variance to be scaled by 1/p. We aim to restore the incoming variance by initializing the\nrespective layers with larger weights. Specifically, we use N (0, 4p/n l ) for layers whose output\nis subject to a GLU and N (0, p/n l ) otherwise (Appendix A.3).\n\nWe consider three major WMT translation tasks as well as a text summarization task.\n\nWMT'16 English-Romanian. We use the same data and pre-processing as Sennrich et al. (2016b) but\nremove sentences with more than 175 words. This results in 2.8M sentence pairs for training and we\nevaluate on newstest2016. 2We experiment with word-based models using a source vocabulary of 200K\ntypes and a target vocabulary of 80K types. We also consider a joint source and target byte-pair\nencoding (BPE) with 40K types (Sennrich et al., 2016a;b).",
    "year": 2017
  },
  {
    "chunk_id": "1705.03122v3.tei.tei_chunk-9",
    "paper_id": "1705.03122v3.tei.tei",
    "section": "4.1. Datasets",
    "paragraph_index": 35,
    "text": "WMT'14 English-German. We use the same setup as Luong et al. (2015) which comprises 4.5M sentence\npairs for training and we test on newstest2014. 3 As vocabulary we use 40K sub-word types based on\nBPE.\n\nWMT'14 English-French. We use the full training set of 36M sentence pairs, and remove sentences\nlonger than 175 words as well as pairs with a source/target length ratio exceeding 1.5. This results\nin 35.5M sentence-pairs for training. Results are reported on newstest2014. We use a source and\ntarget vocabulary with 40K BPE types.\n\nIn all setups a small subset of the training data serves as validation set (about 0.5-1% for each\ndataset) for early stopping and learning rate annealing.\n\nAbstractive summarization. We train on the Gigaword corpus (Graff et al., 2003) and pre-process it\nidentically to Rush et al. (2015) resulting in 3.8M training examples and 190K for validation. We\nevaluate on the DUC-2004 test data comprising 500 article-title pairs (Over et al., 2007) and report\nthree variants of recall-based ROUGE (Lin, 2004), namely, ROUGE-1 (unigrams), ROUGE-2 (bigrams), and\nROUGE-L (longest-common substring). We also evaluate on a Gigaword test set of 2000 pairs which is\nidentical to the one used by Rush et al. (2015) and we report F1 ROUGE similar to prior work.\nSimilar to Shen et al. (2016) we use a source and target vocabulary of 30K words and require outputs\nto be at least 14 words long.\n\nWe use 512 hidden units for both encoders and decoders, unless otherwise stated. All embeddings,\nincluding the output produced by the decoder before the final linear layer, have dimensionality 512;\nwe use the same dimensionalities for linear layers mapping between the hidden and embedding sizes (\n§3.2).",
    "year": 2017
  },
  {
    "chunk_id": "1705.03122v3.tei.tei_chunk-10",
    "paper_id": "1705.03122v3.tei.tei",
    "section": "4.2. Model Parameters and Optimization",
    "paragraph_index": 40,
    "text": "We train our convolutional models with Nesterov's accelerated gradient method (Sutskever et al.,\n2013) using a momentum value of 0.99 and renormalize gradients if their norm exceeds 0.1 (Pascanu et\nal., 2013). We use a learning rate of 0.25 and once the validation perplexity stops improving, we\nreduce the learning rate by an order of magnitude after each epoch until it falls below 10 -4 .\n\nUnless otherwise stated, we use mini-batches of 64 sentences. We restrict the maximum number of\nwords in a mini-batch to make sure that batches with long sentences backtranslations/en-ro.\n\n3 http://nlp.stanford.edu/projects/nmt still fit in GPU memory. If the threshold is exceeded, we\nsimply split the batch until the threshold is met and process the parts separatedly. Gradients are\nnormalized by the number of non-padding tokens per mini-batch. We also use weight normalization for\nall layers except for lookup tables (Salimans & Kingma, 2016).\n\nBesides dropout on the embeddings and the decoder output, we also apply dropout to the input of the\nconvolutional blocks (Srivastava et al., 2014). All models are implemented in Torch (Collobert et\nal., 2011) and trained on a single Nvidia M40 GPU except for WMT'14 English-French for which we use\na multi-GPU setup on a single machine. We train on up to eight GPUs synchronously by maintaining\ncopies of the model on each card and split the batch so that each worker computes 1/8-th of the\ngradients; at the end we sum the gradients via Nvidia NCCL.\n\nWe report average results over three runs of each model, where each differs only in the initial\nrandom seed. Translations are generated by a beam search and we normalize log-likelihood scores by\nsentence length. We use a beam of width 5. We divide the log-likelihoods of the final hypothesis in\nbeam search by their length |y|. For WMT'14 English-German we tune a length normalization constant\non a separate development set (newstest2015) and we normalize log-likelihoods by |y| α (Wu et al.,\n2016). On other datasets we did not find any benefit with length normalization.",
    "year": 2017
  },
  {
    "chunk_id": "1705.03122v3.tei.tei_chunk-11",
    "paper_id": "1705.03122v3.tei.tei",
    "section": "4.3. Evaluation",
    "paragraph_index": 45,
    "text": "For word-based models, we perform unknown word replacement based on attention scores after\ngeneration (Jean et al., 2015). Unknown words are replaced by looking up the source word with the\nmaximum attention score in a precomputed dictionary. If the dictionary contains no translation, then\nwe simply copy the source word. Dictionaries were extracted from the word aligned training data that\nwe obtained with fast align (Dyer et al., 2013). Each source word is mapped to the target word it is\nmost frequently aligned to. In our multi-step attention ( §3.3) we simply average the attention\nscores over all layers. Finally, we compute case-sensitive tokenized BLEU, except for WMT'16\nEnglish-Romanian where we use detokenized BLEU to be comparable with Sennrich et al. (2016b). 4 5.\nResults\n\nWe first evaluate our convolutional model on three translation tasks. On WMT'16 English-Romanian\ntranslation we compare to Sennrich et al. (2016b) which is the winning entry on this language pair\nat WMT'16 (Bojar et al., 2016).\n\nTheir model implements the attention-based sequence to sequence architecture of Bahdanau et al.\n(2014) and uses GRU cells both in the encoder and decoder. We test both word-based and BPE\nvocabularies ( §4).\n\nTable 1 shows that our fully convolutional sequence to sequence model (ConvS2S) outperforms the\nWMT'16 winning entry for English-Romanian by 1.9 BLEU with a BPE encoding and by 1.3 BLEU with a\nword factored vocabulary. This instance of our architecture has 20 layes in the encoder and 20\nlayers in the decoder, both using kernels of width 3 and hidden size 512 throughout. Training took\nbetween 6 and 7.5 days on a single GPU.",
    "year": 2017
  },
  {
    "chunk_id": "1705.03122v3.tei.tei_chunk-12",
    "paper_id": "1705.03122v3.tei.tei",
    "section": "5.1. Recurrent vs. Convolutional Models",
    "paragraph_index": 49,
    "text": "On WMT'14 English to German translation we compare to the following prior work: Luong et al. ( 2015)\nis based on a four layer LSTM attention model, ByteNet (Kalchbrenner et al., 2016) propose a\nconvolutional model based on characters without attention, with 30 layers in the encoder and 30\nlayers in the decoder, GNMT (Wu et al., 2016) represents the state of the art on this dataset and\nthey use eight encoder LSTMs as well as eight decoder LSTMs, we quote their result for a word-based\nmodel, such as ours, as well as a word-piece model (Schuster & Nakajima, 2012). 5\n\nThe results (Table 1) show that our convolutional model outpeforms GNMT by 0.5 BLEU. Our encoder has\n15 layers and the decoder has 15 layers, both with 512 hidden units in the first ten layers and 768\nunits in the subsequent three layers, all using kernel width 3. The final two layers have 2048 units\nwhich are just linear mappings with a single input. We trained this model on a single GPU over a\nperiod of 18.5 days with a batch size of 48. LSTM sparse mixtures have shown strong accuracy at\n26.03 BLEU for a single run (Shazeer et al., 2016) which compares to 25.39 BLEU for our best run.\nThis mixture sums the output of four experts, not unlike an ensemble which sums the output of\nmultiple networks. ConvS2S also benefits from ensembling ( §5.2), therefore mixtures are a promising\ndirection.\n\nFinally, we train on the much larger WMT'14 English-French task where we compare to the state of the\nart result of GNMT (Wu et al., 2016). Our model is trained with a simple token-level likelihood\nobjective and we improve over GNMT in the same setting by 1.6 BLEU on average. We also outperform\ntheir reinforcement (RL) models by 0.5 5 We did not use the exact same vocabulary size because word\npieces and BPE estimate the vocabulary differently. BLEU. Reinforcement learning is equally\napplicable to our architecture and we believe that it would further improve our results.",
    "year": 2017
  },
  {
    "chunk_id": "1705.03122v3.tei.tei_chunk-13",
    "paper_id": "1705.03122v3.tei.tei",
    "section": "5.1. Recurrent vs. Convolutional Models",
    "paragraph_index": 52,
    "text": "The ConvS2S model for this experiment uses 15 layers in the encoder and 15 layers in the decoder,\nboth with 512 hidden units in the first five layers, 768 units in the subsequent four layers, 1024\nunits in the next 3 layers, all using kernel width 3; the final two layers have 2048 units and 4096\nunits each but the they are linear mappings with kernel width 1. This model has an effective context\nsize of only 25 words, beyond which it cannot access any information on the target size. Our results\nare based on training with 8 GPUs for about 37 days and batch size 32 on each worker. 6 The same\nconfiguration as for WMT'14 English-German achieves 39.41 BLEU in two weeks on this dataset in an\neight GPU setup. The translations produced by our models often match the length of the references,\nparticularly for the large WMT'14 English-French task, or are very close for small to medium data\nsets such as WMT'14 English-German or WMT'16 English-Romanian.\n\nNext, we ensemble eight likelihood-trained models for both WMT'14 English-German and WMT'14 English-\nFrench and compare to previous work which also reported ensemble results. For the former, we also\nshow the result when ensembling 10 models. Table 2 shows that we outperform the best current\nensembles on both datasets.\n\nNext, we evaluate the inference speed of our architecture on the development set of the WMT'14\nEnglish-French task which is the concatenation of newstest2012 and new-stest2013; it comprises 6003\nsentences. We measure generation speed both on GPU and CPU hardware. Specifically, we measure GPU\nspeed on three generations of Nvidia cards: a GTX-1080ti, an M40 as well as an older K40 card. CPU\ntimings are measured on one host with 48 hyperthreaded cores (Intel Xeon E5-2680 @ 2.50GHz) with 40\nworkers. In all settings, we batch up to 128 sentences, composing batches with sentences of equal\nlength. Note that the majority of batches is smaller because of the small size of the development\nset. We experiment with beams of size 5 as well as greedy search, i.e beam of size 1. To make\ngeneration fast, we do not recompute convolution states that have not changed compared to the\nprevious time step but rather copy (shift) these activations.",
    "year": 2017
  },
  {
    "chunk_id": "1705.03122v3.tei.tei_chunk-14",
    "paper_id": "1705.03122v3.tei.tei",
    "section": "5.3. Generation Speed",
    "paragraph_index": 55,
    "text": "We compare to results reported in Wu et al. (2016) who use Nvidia K80 GPUs which are essentially two\nK40s. We did not have such a GPU available and therefore run experiments on an older K40 card which\nis inferior to a K80, in addition to the newer M40 and GTX-1080ti cards. The results (Table 3) show\nthat our model can generate translations on a K40 GPU at 9.3 times the speed and 2.25 higher BLEU;\non an M40 the speed-up is up to 13.7 times and on a GTX-1080ti card the speed is 21.3 times faster.\nA larger beam of size 5 decreases speed but gives better BLEU.\n\nOn CPU, our model is up to 9.3 times faster, however, the GNMT CPU results were obtained with an 88\ncore machine whereas our results were obtained with just over half the number of cores. On a per CPU\ncore basis, our model is 17 times faster at a better BLEU. Finally, our CPU speed is 2.7 times\nhigher than GNMT on a custom TPU chip which shows that high speed can be achieved on commodity\nhardware. We do no report TPU figures as we do not have access to this hardware.\n\nIn the following sections, we analyze the design choices in our architecture. The remaining results\nin this paper are based on the WMT'14 English-German task with 13 encoder layers at kernel size 3\nand 5 decoder layers at kernel size 5. We use a target vocabulary of 160K words as well as\nvocabulary selection (Mi et al., 2016;L'Hostis et al., 2016) to decrease the size of the output\nlayer which speeds up training and testing. The average vocabulary size for each training batch is\nabout 20K target words. All figures are averaged over three runs ( §4) and BLEU is reported on new-\nstest2014 before unknown word replacement.",
    "year": 2017
  },
  {
    "chunk_id": "1705.03122v3.tei.tei_chunk-15",
    "paper_id": "1705.03122v3.tei.tei",
    "section": "5.4. Position Embeddings",
    "paragraph_index": 58,
    "text": "We start with an experiment that removes the position em- beddings from the encoder and decoder (\n§3.1). These embeddings allow our model to identify which portion of the source and target sequence\nit is dealing with but also impose a restriction on the maximum sentence length. Table 4 shows that\nposition embeddings are helpful but that our model still performs well without them. Removing the\nsource position embeddings results in a larger accuracy decrease than target position embeddings.\nHowever, removing both source and target positions decreases accuracy only by 0.5 BLEU. We had\nassumed that the model would not be able to calibrate the length of the output sequences very well\nwithout explicit position information, however, the output lengths of models without position\nembeddings closely matches models with position information. This indicates that the models can\nlearn relative position information within the contexts visible to the encoder and decoder networks\nwhich can observe up to 27 and 25 words respectively.\n\nRecurrent models typically do not use explicit position embeddings since they can learn where they\nare in the sequence through the recurrent hidden state computation. In our setting, the use of\nposition embeddings requires only a simple addition to the input word embeddings which is a\nnegligible overhead.\n\nThe multiple attention mechanism ( §3.3) computes a separate source context vector for each decoder\nlayer. The computation also takes into account contexts computed for preceding decoder layers of the\ncurrent time step as well as previous time steps that are within the receptive field of the decoder.\nHow does multiple attention compare to attention in fewer layers or even only in a single layer as\nis usual? Table 5 shows that attention in all decoder layers achieves the best validation perplexity\n(PPL). Furthermore, removing more and more attention layers decreases accuracy, both in terms of\nBLEU as well as PPL.\n\nThe computational overhead for attention is very small compared to the rest of the network. a 4%\nslow down when adding 4 attention modules. Most neural machine translation systems only use a single\nmodule. This demonstrates that attention is not the bottleneck in neural machine translation, even\nthough it is quadratic in the sequence length (cf. Kalchbrenner et al., 2016). Part of the reason\nfor the low impact on speed is that we batch the computation of an attention module over all target\nwords, similar to Kalchbrenner et al. (2016). However, for RNNs batching of the attention may be\nless effective because of the dependence on the previous time step.",
    "year": 2017
  },
  {
    "chunk_id": "1705.03122v3.tei.tei_chunk-16",
    "paper_id": "1705.03122v3.tei.tei",
    "section": "5.6. Kernel size and Depth",
    "paragraph_index": 62,
    "text": "Figure 2 shows accuracy when we change the number of layers in the encoder or decoder. The kernel\nwidth for layers in the encoder is 3 and for the decoder it is 5. Deeper architectures are\nparticularly beneficial for the encoder but less so for the decoder. Decoder setups with two layers\nalready perform well whereas for the encoder accuracy keeps increasing steadily with more layers\nuntil up to 9 layers when accuracy starts to plateau.\n\nRNN MLE (Shen et al., 2016) 24 Aside from increasing the depth of the networks, we can also change\nthe kernel width. Table 7 shows that encoders with narrow kernels and many layers perform better\nthan wider kernels. These networks can also be faster since the amount of work to compute a kernel\noperating over 3 input elements is less than half compared to kernels over 7 elements. We see a\nsimilar picture for decoder networks with large kernel sizes (Table 8). Dauphin et al. (2016) shows\nthat context sizes of 20 words are often sufficient to achieve very good accuracy on language\nmodeling for English.\n\nFinally, we evaluate our model on abstractive sentence summarization which takes a long sentence as\ninput and outputs a shortened version. The current best models on this task are recurrent neural\nnetworks which either optimize the evaluation metric (Shen et al., 2016) or address specific\nproblems of summarization such as avoiding repeated generations (Suzuki & Nagata, 2017). We use\nstandard likelhood training for our model and a simple model with six layers in the encoder and\ndecoder each, hidden size 256, batch size 128, and we trained on a single GPU in one night. Table 6\nshows that our likelhood trained model outperforms the likelihood trained model (RNN MLE) of Shen et\nal. (2016) and is not far behind the best models on this task which benefit from task-specific\noptimization and model structure. We expect our model to benefit from these improvements as well.",
    "year": 2017
  },
  {
    "chunk_id": "1705.03122v3.tei.tei_chunk-17",
    "paper_id": "1705.03122v3.tei.tei",
    "section": "6. Conclusion and Future Work",
    "paragraph_index": 65,
    "text": "We introduce the first fully convolutional model for sequence to sequence learning that outperforms\nstrong recurrent models on very large benchmark datasets at an order of magnitude faster speed.\nCompared to recurrent networks, our convolutional approach allows to discover compositional\nstructure in the sequences more easily since representations are built hierarchically. Our model\nrelies on gating and performs multiple attention steps.\n\nWe achieve a new state of the art on several public translation benchmark data sets. On the WMT'16\nEnglish-Romanian task we outperform the previous best result by 1.9 BLEU, on WMT'14 English-French\ntranslation we improve over the LSTM model of Wu et al. (2016) by 1.6 BLEU in a comparable setting,\nand on WMT'14 English-German translation we ouperform the same model by 0.5 BLEU. In future work, we\nwould like to apply convolutional architectures to other sequence to sequence learning problems\nwhich may benefit from learning hierarchical representations as well.\n\nand 6 exhibit a linear alignment. The first layer shows the clearest alignment, although it is\nslightly off and frequently attends to the corresponding source word of the previously generated\ntarget word. Layer 2 and 8 lack a clear structure and are presumably collecting information about\nthe whole source sentence. The fourth layer shows high alignment scores on nouns such as \"festival\",\n\"way\" and \"work\" for both the generated target nouns as well as their preceding words. Note that in\nGerman, those preceding words depend on gender and object relationship of the respective noun.\nFinally, the attention scores in layer 5 and 7 focus on \"built\", which is reordered in the German\ntranslation and is moved from the beginning to the very end of the sentence. One interpretation for\nthis is that as generation progresses, the model repeatedly tries to perform the re-ordering.\n\"aufgebaut\" can be generated after a noun or pronoun only, which is reflected in the higher scores\nat positions 2, 5, 8, 11 and 13.",
    "year": 2017
  },
  {
    "chunk_id": "1705.03122v3.tei.tei_chunk-18",
    "paper_id": "1705.03122v3.tei.tei",
    "section": "6. Conclusion and Future Work",
    "paragraph_index": 68,
    "text": "---\n## Footnotes\n\n[1] The source code and models are available at https:// github.com/facebookresearch/fairseq.\n\n[2] We followed the pre-processing of https://github. com/rsennrich/wmt16-scripts/blob/80e21e5/\nsample/preprocess.sh and added the back-translated data from http://data.statmt.org/rsennrich/wmt16_\n\n[4] https://github.com/moses-smt/ mosesdecoder/blob/617e8c8/scripts/generic/ {multi-\nbleu.perl,mteval-v13a.pl}\n\n[6] This is half of the GPU time consumed by a basic model ofWu et al. (2016) who use 96 GPUs for 6\ndays. We expect the time to train our model to decrease substantially in a multi-machine setup.",
    "year": 2017
  }
]